configgraphviz/__init__.py
configgraphviz/graph_builder.py
configgraphviz/parsers.py
configgraphviz-0.1.1.dist-info/licenses/LICENSE
configgraphviz-0.1.1.dist-info/METADATA
configgraphviz-0.1.1.dist-info/WHEEL
configgraphviz-0.1.1.dist-info/top_level.txt
configgraphviz-0.1.1.dist-info/RECORD
