Metadata-Version: 2.4
Name: configgraphviz
Version: 0.1.1
Summary: Generate Graphviz DOT visualizations from INI, YAML, and TOML configuration files.
Author-email: Richard CHAN <richard.mychan@gmail.com>
License: MIT
Project-URL: Homepage, https://github.com/manyan-chan/ConfigGraphViz
Project-URL: Repository, https://github.com/manyan-chan/ConfigGraphViz
Keywords: config,configuration,graphviz,dot,visualize,ini,yaml,toml,parser,diagram
Classifier: Development Status :: 4 - Beta
Classifier: Intended Audience :: Developers
Classifier: Intended Audience :: System Administrators
Classifier: License :: OSI Approved :: MIT License
Classifier: Operating System :: OS Independent
Classifier: Programming Language :: Python :: 3
Classifier: Programming Language :: Python :: 3.8
Classifier: Programming Language :: Python :: 3.9
Classifier: Programming Language :: Python :: 3.10
Classifier: Programming Language :: Python :: 3.11
Classifier: Programming Language :: Python :: 3.12
Classifier: Topic :: Software Development :: Libraries :: Python Modules
Classifier: Topic :: Software Development :: Code Generators
Classifier: Topic :: System :: Systems Administration
Classifier: Topic :: Utilities
Classifier: Typing :: Typed
Requires-Python: >=3.8
License-File: LICENSE
Requires-Dist: PyYAML>=5.1
Requires-Dist: tomli>=1.1.0; python_version < "3.11"
Provides-Extra: test
Requires-Dist: pytest>=7.0; extra == "test"
Requires-Dist: pytest-cov; extra == "test"
Dynamic: license-file
